README.md
issh.py
setup.py
issh.egg-info/PKG-INFO
issh.egg-info/SOURCES.txt
issh.egg-info/dependency_links.txt
issh.egg-info/entry_points.txt
issh.egg-info/not-zip-safe
issh.egg-info/top_level.txt