Metadata-Version: 2.1
Name: issh
Version: 1.4.1
Summary: Improved SSH: TUI menu for connecting to SSH config hosts
Home-page: https://github.com/DevDungeon/issh
Author: DevDungeon
Author-email: nanodano@devdungeon.com
License: UNKNOWN
Platform: UNKNOWN
Classifier: License :: OSI Approved :: GNU General Public License v3 (GPLv3)
